image_processing_vosaito/__init__.py
image_processing_vosaito/processing/__init__.py
image_processing_vosaito/processing/combination.py
image_processing_vosaito/processing/transformation.py
image_processing_vosaito/utils/__init__.py
image_processing_vosaito/utils/io.py
image_processing_vosaito/utils/plot.py
image_processing_vosaito-0.0.1.dist-info/METADATA
image_processing_vosaito-0.0.1.dist-info/WHEEL
image_processing_vosaito-0.0.1.dist-info/top_level.txt
image_processing_vosaito-0.0.1.dist-info/RECORD
