Metadata-Version: 2.2
Name: image_processing_vosaito
Version: 0.0.1
Summary: Image processing package using skimage. This project belongs to Karina Tiemi Kato. E-mail:karinatkato@gmail.com.
Home-page: https://github.com/vosaito/image-processing-package
Author: Victor Saito
Author-email: victorsaito871@gmail.com
Requires-Python: >=3.5
Requires-Dist: setuptools
Requires-Dist: numpy
Requires-Dist: scikit-image
Requires-Dist: matplotlib
Dynamic: author
Dynamic: author-email
Dynamic: description
Dynamic: description-content-type
Dynamic: home-page
Dynamic: requires-dist
Dynamic: requires-python
Dynamic: summary
